keras_datasets/__init__.py
keras_datasets/datasets.py
keras_datasets/exceptions.py
keras_datasets/utils.py
keras_datasets-0.1.0.dist-info/DESCRIPTION.rst
keras_datasets-0.1.0.dist-info/METADATA
keras_datasets-0.1.0.dist-info/RECORD
keras_datasets-0.1.0.dist-info/WHEEL
keras_datasets-0.1.0.dist-info/metadata.json
keras_datasets-0.1.0.dist-info/top_level.txt
