Metadata-Version: 1.0
Name: keras-datasets
Version: 0.1.0
Summary: UNKNOWN
Home-page: UNKNOWN
Author: UNKNOWN
Author-email: UNKNOWN
License: Creative Commons Attribution-Noncommercial-Share Alike license
Platform: UNKNOWN
